birdhousebuilder.recipe.thredds-0.3.0-py2.7-nspkg.pth
birdhousebuilder/recipe/thredds/__init__.py
birdhousebuilder/recipe/thredds/catalog.xml
birdhousebuilder/recipe/thredds/threddsConfig.xml
birdhousebuilder/recipe/thredds/wmsConfig.xml
birdhousebuilder/recipe/thredds/tests/__init__.py
birdhousebuilder/recipe/thredds/tests/test_docs.py
birdhousebuilder.recipe.thredds-0.3.0.dist-info/DESCRIPTION.rst
birdhousebuilder.recipe.thredds-0.3.0.dist-info/METADATA
birdhousebuilder.recipe.thredds-0.3.0.dist-info/RECORD
birdhousebuilder.recipe.thredds-0.3.0.dist-info/WHEEL
birdhousebuilder.recipe.thredds-0.3.0.dist-info/entry_points.txt
birdhousebuilder.recipe.thredds-0.3.0.dist-info/metadata.json
birdhousebuilder.recipe.thredds-0.3.0.dist-info/namespace_packages.txt
birdhousebuilder.recipe.thredds-0.3.0.dist-info/pbr.json
birdhousebuilder.recipe.thredds-0.3.0.dist-info/top_level.txt
